sop/__init__.py
sop/btree.py
sop/call_go.py
sop/context.py
sop/libjsondb_amd64darwin.dylib
sop/libjsondb_amd64darwin.h
sop/libjsondb_amd64linux.h
sop/libjsondb_amd64linux.so
sop/libjsondb_amd64windows.dll
sop/libjsondb_amd64windows.h
sop/libjsondb_arm64darwin.dylib
sop/libjsondb_arm64darwin.h
sop/libjsondb_arm64linux.h
sop/libjsondb_arm64linux.so
sop/redis.py
sop/test_btree.py
sop/test_btree_idx.py
sop/transaction.py
sop_python_beta_3-3.0.9.dist-info/METADATA
sop_python_beta_3-3.0.9.dist-info/WHEEL
sop_python_beta_3-3.0.9.dist-info/top_level.txt
sop_python_beta_3-3.0.9.dist-info/RECORD
