Metadata-Version: 2.4
Name: sop-python-beta-3
Version: 3.0.9
Summary: Scalable Objects Persistence for Python.
Author-email: Gerardo Recinto <gerardorecinto@yahoo.com>
Classifier: Programming Language :: Python :: 3
Classifier: License :: OSI Approved :: MIT License
Classifier: Operating System :: OS Independent
Requires-Python: >=3.7
